gitstats/__init__.py
gitstats/assets/arrow-down.gif
gitstats/assets/arrow-none.gif
gitstats/assets/arrow-up.gif
gitstats/assets/gitstats.css
gitstats/assets/sortable.js
gitstats/collector.py
gitstats/config.py
gitstats/gitstats.py
gitstats/main.py
gitstats/report.py
gitstats/utils.py
gitstats/version.py
gitstats_abilian-1.0.6.dist-info/METADATA
gitstats_abilian-1.0.6.dist-info/WHEEL
gitstats_abilian-1.0.6.dist-info/entry_points.txt
gitstats_abilian-1.0.6.dist-info/RECORD
