Metadata-Version: 2.1
Name: gitstats-abilian
Version: 1.0.6
Summary: 
Author: Stefane Fermigier
Author-email: sf@abilian.com
Requires-Python: >=3.9,<4.0
Classifier: Programming Language :: Python :: 3
Classifier: Programming Language :: Python :: 3.9
Classifier: Programming Language :: Python :: 3.10
Classifier: Programming Language :: Python :: 3.11
Classifier: Programming Language :: Python :: 3.12
